acs_wrapper/__init__.py
acs_wrapper/acs.py
acs_wrapper/acs_process.py
acs_wrapper/notebook/__init__.py
acs_wrapper/src/__init__.py
acs_wrapper/src/pandas_util.py
acs_wrapper/src/parameters.py
acs_wrapper/src/util_multiprocessing.py
acs_wrapper/src/read/__init__.py
acs_wrapper/src/read/acs_read_base.py
acs_wrapper/src/read/implementations/__init__.py
acs_wrapper/src/read/implementations/acs_read_age.py
acs_wrapper/src/read/implementations/acs_read_age65.py
acs_wrapper/src/read/implementations/acs_read_education.py
acs_wrapper/src/read/implementations/acs_read_income.py
acs_wrapper/src/read/implementations/acs_read_race.py
acs_wrapper/src/read/implementations/acs_read_total_population.py
acs_wrapper/src/read/implementations/acs_read_type_health_insurance_age.py
old/__init__.py
old/acs_read.py
old/common.py
old/script_acs.py
old/preprocess/__init__.py
old/preprocess/acs_zcta.py
old/preprocess/join_acs.py
old/script/__init__.py
old/script/acs_preprocess.py
acs_wrapper-1.0.17.dist-info/METADATA
acs_wrapper-1.0.17.dist-info/WHEEL
acs_wrapper-1.0.17.dist-info/top_level.txt
acs_wrapper-1.0.17.dist-info/RECORD
