Metadata-Version: 2.1
Name: acs-wrapper
Version: 1.0.17
Summary: A wrapper for the American Community Survey Data
Home-page: https://github.com/diegompin/american-community-survey
Author: Diego Pinheiro
Author-email: diegompin@gmail.com
License: UNKNOWN
Platform: UNKNOWN
Classifier: Programming Language :: Python :: 3
Requires-Dist: pandas
